caddy_api_client/__init__.py
caddy_api_client/client.py
caddy_api_client-0.2.5.dist-info/AUTHORS
caddy_api_client-0.2.5.dist-info/LICENSE
caddy_api_client-0.2.5.dist-info/METADATA
caddy_api_client-0.2.5.dist-info/WHEEL
caddy_api_client-0.2.5.dist-info/top_level.txt
caddy_api_client-0.2.5.dist-info/RECORD
