Metadata-Version: 2.1
Name: caddy-api-client
Version: 0.2.5
Summary: A Python client for the Caddy API
Home-page: https://github.com/migetapp/caddy-api-client
Author: Krzysztof Taraszka
Author-email: chris@miget.com
Classifier: Development Status :: 4 - Beta
Classifier: Intended Audience :: Developers
Classifier: Programming Language :: Python :: 3
Classifier: Programming Language :: Python :: 3.7
Classifier: Programming Language :: Python :: 3.8
Classifier: Programming Language :: Python :: 3.9
Classifier: Programming Language :: Python :: 3.10
Classifier: Topic :: Internet :: WWW/HTTP :: HTTP Servers
Classifier: Topic :: Software Development :: Libraries :: Python Modules
Requires-Python: >=3.7
License-File: LICENSE
License-File: AUTHORS
Requires-Dist: requests>=2.31.0
